superleaptestv1/__init__.py
superleaptestv1/client.py
sachin_super_test-0.1.0.dist-info/LICENCE
sachin_super_test-0.1.0.dist-info/METADATA
sachin_super_test-0.1.0.dist-info/WHEEL
sachin_super_test-0.1.0.dist-info/top_level.txt
sachin_super_test-0.1.0.dist-info/RECORD
