Metadata-Version: 2.1
Name: sachin-super-test
Version: 0.1.0
Summary: A Python SDK for the Superleap API
Home-page: https://github.com/superleapai/superleap-sdk
Author: Sachin Kant
Author-email: sachin-ext@superleap.com
Classifier: Programming Language :: Python :: 3
Classifier: License :: OSI Approved :: MIT License
Classifier: Operating System :: OS Independent
Requires-Python: >=3.7
License-File: LICENCE
Requires-Dist: requests>=2.25.0
